{
    "attributes": [
        {
            "pants_type": "Split Color Boxers",
            "pants_color": "Blue",
            "secondary_pants_color": "Purple",
            "shirt_type": "Full Sleeve Split Color Jacket",
            "shirt_color": "Blue",
            "secondary_shirt_color": "Light Blue",
            "hat_type": "Normal Hair",
            "hat_color": "White",
            "skin_color": "Green",
            "eye_type": "Plus Eyes",
            "element_type": "Ice",
            "head_effect": "Spikes"
        }
    ]
}