{
    "attributes": [
        {
            "pants_type": "Split Color Jeans",
            "pants_color": "Light Orange",
            "secondary_pants_color": "White",
            "shirt_type": "Short Sleeve Split Color Jacket",
            "shirt_color": "Yellow",
            "secondary_shirt_color": "Pink",
            "hat_type": "Baseball Hat",
            "hat_color": "Orange",
            "skin_color": "Purple",
            "eye_type": "Confused Eyes",
            "element_type": "Fire",
            "head_effect": "Shield"
        }
    ]
}