{
    "attributes": [
        {
            "pants_type": "Bottomless Jeans",
            "pants_color": "Light Blue",
            "secondary_pants_color": "Light Blue",
            "shirt_type": "Full Sleeve Jacket",
            "shirt_color": "Light Yellow",
            "secondary_shirt_color": "Light Red",
            "hat_type": "Puffballs",
            "hat_color": "White",
            "skin_color": "Glass Cyan",
            "eye_type": "Closed Eyes",
            "element_type": "Space",
            "head_effect": "Regeneration"
        }
    ]
}