{
    "attributes": [
        {
            "pants_type": "Shorts",
            "pants_color": "Gray",
            "secondary_pants_color": "Tan",
            "shirt_type": "Full Sleeve Split Color Jacket",
            "shirt_color": "Dark Purple",
            "secondary_shirt_color": "Dark Red",
            "hat_type": "Normal Hair",
            "hat_color": "Yellow",
            "skin_color": "Purple",
            "eye_type": "Happy Eyes",
            "element_type": "Space",
            "head_effect": "Green Cross"
        }
    ]
}