{
    "attributes": [
        {
            "pants_type": "Bottomless Jeans",
            "pants_color": "Red",
            "secondary_pants_color": "Pink",
            "shirt_type": "Short Sleeve Jacket",
            "shirt_color": "Dark Pink",
            "secondary_shirt_color": "Dark Blue",
            "hat_type": "Top Hat",
            "hat_color": "Light Green",
            "skin_color": "Orange",
            "eye_type": "Standard Eyes",
            "element_type": "Nature",
            "head_effect": "Mystery"
        }
    ]
}