{
    "attributes": [
        {
            "pants_type": "Bottomless Jeans",
            "pants_color": "Red",
            "secondary_pants_color": "Light Blue",
            "shirt_type": "Full Sleeve Jacket",
            "shirt_color": "Light Pink",
            "secondary_shirt_color": "Yellow",
            "hat_type": "Mohawk",
            "hat_color": "Yellow",
            "skin_color": "Glass Purple",
            "eye_type": "Circle Eyes",
            "element_type": "Air",
            "head_effect": "Ice"
        }
    ]
}