{
    "attributes": [
        {
            "pants_type": "Bottomless Jeans",
            "pants_color": "Dark Green",
            "secondary_pants_color": "Gray",
            "shirt_type": "Full Sleeve Split Color Jacket",
            "shirt_color": "White",
            "secondary_shirt_color": "Red",
            "hat_type": "Normal Hair",
            "hat_color": "Dark Red",
            "skin_color": "Skin Tone 5",
            "eye_type": "Double S Eyes",
            "element_type": "Earth",
            "head_effect": "Omega Hole"
        }
    ]
}