{
    "attributes": [
        {
            "pants_type": "Boxers",
            "pants_color": "Pink",
            "secondary_pants_color": "Light Tan",
            "shirt_type": "Full Sleeve Split Color Jacket",
            "shirt_color": "White",
            "secondary_shirt_color": "Dark Orange",
            "hat_type": "Headband",
            "hat_color": "Dark Orange",
            "skin_color": "Green",
            "eye_type": "Out Eyes",
            "element_type": "Ice",
            "head_effect": "Speed"
        }
    ]
}