{
    "attributes": [
        {
            "pants_type": "Boxers",
            "pants_color": "Dark Blue",
            "secondary_pants_color": "Light Orange",
            "shirt_type": "Short Sleeve Split Color Jacket",
            "shirt_color": "Dark Blue",
            "secondary_shirt_color": "Pink",
            "hat_type": "No Hat",
            "hat_color": "Red",
            "skin_color": "Glass Pink",
            "eye_type": "Happy Eyes",
            "element_type": "Air",
            "head_effect": "Ammo"
        }
    ]
}