{
    "attributes": [
        {
            "pants_type": "Bottomless Jeans",
            "pants_color": "Light Orange",
            "secondary_pants_color": "Red",
            "shirt_type": "Short Sleeve Split Color Jacket",
            "shirt_color": "Dark Gray",
            "secondary_shirt_color": "Dark Purple",
            "hat_type": "Beret",
            "hat_color": "Brown",
            "skin_color": "Skin Tone 4",
            "eye_type": "Plus Eyes",
            "element_type": "Nature",
            "head_effect": "Green Cross"
        }
    ]
}