{
    "attributes": [
        {
            "pants_type": "Split Color Jeans",
            "pants_color": "Gray",
            "secondary_pants_color": "Light Orange",
            "shirt_type": "Short Sleeve Jacket",
            "shirt_color": "Dark Blue",
            "secondary_shirt_color": "Brown",
            "hat_type": "Aviator Hat",
            "hat_color": "Dark Yellow",
            "skin_color": "Glass Yellow",
            "eye_type": "Confused Eyes",
            "element_type": "Metal",
            "head_effect": "Regeneration"
        }
    ]
}