{
    "attributes": [
        {
            "pants_type": "Shorts",
            "pants_color": "Dark Blue",
            "secondary_pants_color": "Dark Green",
            "shirt_type": "Short Sleeve Split Color Jacket",
            "shirt_color": "Red",
            "secondary_shirt_color": "Orange",
            "hat_type": "Aviator Hat",
            "hat_color": "Orange",
            "skin_color": "Green",
            "eye_type": "Standard Eyes",
            "element_type": "Earth",
            "head_effect": "Spikes"
        }
    ]
}