{
    "attributes": [
        {
            "pants_type": "Shorts",
            "pants_color": "Black",
            "secondary_pants_color": "Green",
            "shirt_type": "Full Sleeve Jacket",
            "shirt_color": "Dark Blue",
            "secondary_shirt_color": "Pink",
            "hat_type": "Headband",
            "hat_color": "Pink",
            "skin_color": "Pink",
            "eye_type": "Circle Eyes",
            "element_type": "Ice",
            "head_effect": "Mystery"
        }
    ]
}