{
    "attributes": [
        {
            "pants_type": "Shorts",
            "pants_color": "Light Green",
            "secondary_pants_color": "Black",
            "shirt_type": "Full Sleeve Split Color Jacket",
            "shirt_color": "Dark Orange",
            "secondary_shirt_color": "Yellow",
            "hat_type": "Hat With No Brim",
            "hat_color": "Dark Yellow",
            "skin_color": "Skin Tone 6",
            "eye_type": "Cautious Eyes",
            "element_type": "Metal",
            "head_effect": "Ice"
        }
    ]
}