{
    "attributes": [
        {
            "pants_type": "Bottomless Jeans",
            "pants_color": "Dark Green",
            "secondary_pants_color": "Dark Green",
            "shirt_type": "Sleeveless Jacket",
            "shirt_color": "Dark Gray",
            "secondary_shirt_color": "Purple",
            "hat_type": "No Hat",
            "hat_color": "Dark Gray",
            "skin_color": "Purple",
            "eye_type": "Plus Eyes",
            "element_type": "Earth",
            "head_effect": "Smoke"
        }
    ]
}